./.gitignore
./.python-version
./PKG-INFO
./README.md
./mcp_client.py
./pyproject.toml
./requirements.txt
./test_filtering.py
./uv.lock
mcp_server_trello-0.1.1.dist-info/METADATA
mcp_server_trello-0.1.1.dist-info/WHEEL
mcp_server_trello-0.1.1.dist-info/entry_points.txt
mcp_server_trello-0.1.1.dist-info/RECORD
