Metadata-Version: 2.4
Name: mcp-server-trello
Version: 0.1.1
Summary: MCP server for Trello API integration
Author-email: Liad Goren <khgs2411@gmail.com>
Requires-Python: >=3.10
Requires-Dist: fastmcp>=2.12.4
Requires-Dist: requests>=2.32.5
